ai/backend/accelerator/cuda_open/VERSION
ai/backend/accelerator/cuda_open/__init__.py
ai/backend/accelerator/cuda_open/nvidia.py
ai/backend/accelerator/cuda_open/plugin.py
ai/backend/accelerator/cuda_open/py.typed
backend_ai_accelerator_cuda_open-26.1.0.dist-info/METADATA
backend_ai_accelerator_cuda_open-26.1.0.dist-info/WHEEL
backend_ai_accelerator_cuda_open-26.1.0.dist-info/entry_points.txt
backend_ai_accelerator_cuda_open-26.1.0.dist-info/namespace_packages.txt
backend_ai_accelerator_cuda_open-26.1.0.dist-info/top_level.txt
backend_ai_accelerator_cuda_open-26.1.0.dist-info/RECORD
